csbtoolkit/__init__.py
csbtoolkit/georeference.py
csbtoolkit/uncertainty.py
csbtoolkit-0.1.0.dist-info/LICENSE
csbtoolkit-0.1.0.dist-info/METADATA
csbtoolkit-0.1.0.dist-info/WHEEL
csbtoolkit-0.1.0.dist-info/top_level.txt
csbtoolkit-0.1.0.dist-info/RECORD
