Metadata-Version: 2.1
Name: csbtoolkit
Version: 0.1.0
Summary: Crowdsourced bathymetry toolkit
Author: Guillaume Morissette
Author-email: guillaume.morissette@cidco.ca
Classifier: Programming Language :: Python :: 3
Classifier: License :: OSI Approved :: MIT License
Classifier: Operating System :: OS Independent
Requires-Python: >=3.6
License-File: LICENSE
